{
  "version": "6",
  "dialect": "sqlite",
  "id": "540061e4-110c-4ab4-a8cc-af05cda7c096",
  "prevId": "00000000-0000-0000-0000-000000000000",
  "tables": {
    "issues": {
      "name": "issues",
      "columns": {
        "id": {
          "name": "id",
          "type": "integer",
          "primaryKey": true,
          "notNull": true,
          "autoincrement": true
        },
        "issue_id": {
          "name": "issue_id",
          "type": "integer",
          "primaryKey": false,
          "notNull": true,
          "autoincrement": false
        },
        "phase": {
          "name": "phase",
          "type": "text",
          "primaryKey": false,
          "notNull": true,
          "autoincrement": false
        },
        "status": {
          "name": "status",
          "type": "text",
          "primaryKey": false,
          "notNull": true,
          "autoincrement": false
        },
        "session_id": {
          "name": "session_id",
          "type": "text",
          "primaryKey": false,
          "notNull": false,
          "autoincrement": false
        },
        "pid": {
          "name": "pid",
          "type": "integer",
          "primaryKey": false,
          "notNull": false,
          "autoincrement": false
        },
        "plan_summary": {
          "name": "plan_summary",
          "type": "text",
          "primaryKey": false,
          "notNull": false,
          "autoincrement": false
        },
        "mr_url": {
          "name": "mr_url",
          "type": "text",
          "primaryKey": false,
          "notNull": false,
          "autoincrement": false
        },
        "error": {
          "name": "error",
          "type": "text",
          "primaryKey": false,
          "notNull": false,
          "autoincrement": false
        },
        "issue_url": {
          "name": "issue_url",
          "type": "text",
          "primaryKey": false,
          "notNull": false,
          "autoincrement": false
        },
        "started_at": {
          "name": "started_at",
          "type": "text",
          "primaryKey": false,
          "notNull": false,
          "autoincrement": false
        },
        "finished_at": {
          "name": "finished_at",
          "type": "text",
          "primaryKey": false,
          "notNull": false,
          "autoincrement": false
        },
        "created_at": {
          "name": "created_at",
          "type": "text",
          "primaryKey": false,
          "notNull": true,
          "autoincrement": false,
          "default": "(datetime('now'))"
        },
        "updated_at": {
          "name": "updated_at",
          "type": "text",
          "primaryKey": false,
          "notNull": true,
          "autoincrement": false,
          "default": "(datetime('now'))"
        }
      },
      "indexes": {
        "issues_issue_id_unique": {
          "name": "issues_issue_id_unique",
          "columns": [
            "issue_id"
          ],
          "isUnique": true
        }
      },
      "foreignKeys": {},
      "compositePrimaryKeys": {},
      "uniqueConstraints": {},
      "checkConstraints": {}
    },
    "plans": {
      "name": "plans",
      "columns": {
        "id": {
          "name": "id",
          "type": "integer",
          "primaryKey": true,
          "notNull": true,
          "autoincrement": true
        },
        "issue_id": {
          "name": "issue_id",
          "type": "integer",
          "primaryKey": false,
          "notNull": true,
          "autoincrement": false
        },
        "content": {
          "name": "content",
          "type": "text",
          "primaryKey": false,
          "notNull": true,
          "autoincrement": false
        },
        "created_at": {
          "name": "created_at",
          "type": "text",
          "primaryKey": false,
          "notNull": true,
          "autoincrement": false,
          "default": "(datetime('now'))"
        },
        "updated_at": {
          "name": "updated_at",
          "type": "text",
          "primaryKey": false,
          "notNull": true,
          "autoincrement": false,
          "default": "(datetime('now'))"
        }
      },
      "indexes": {
        "plans_issue_id_unique": {
          "name": "plans_issue_id_unique",
          "columns": [
            "issue_id"
          ],
          "isUnique": true
        }
      },
      "foreignKeys": {
        "plans_issue_id_issues_issue_id_fk": {
          "name": "plans_issue_id_issues_issue_id_fk",
          "tableFrom": "plans",
          "tableTo": "issues",
          "columnsFrom": [
            "issue_id"
          ],
          "columnsTo": [
            "issue_id"
          ],
          "onDelete": "no action",
          "onUpdate": "no action"
        }
      },
      "compositePrimaryKeys": {},
      "uniqueConstraints": {},
      "checkConstraints": {}
    },
    "qa_criteria": {
      "name": "qa_criteria",
      "columns": {
        "id": {
          "name": "id",
          "type": "integer",
          "primaryKey": true,
          "notNull": true,
          "autoincrement": true
        },
        "issue_id": {
          "name": "issue_id",
          "type": "integer",
          "primaryKey": false,
          "notNull": true,
          "autoincrement": false
        },
        "data": {
          "name": "data",
          "type": "text",
          "primaryKey": false,
          "notNull": true,
          "autoincrement": false
        },
        "created_at": {
          "name": "created_at",
          "type": "text",
          "primaryKey": false,
          "notNull": true,
          "autoincrement": false,
          "default": "(datetime('now'))"
        },
        "updated_at": {
          "name": "updated_at",
          "type": "text",
          "primaryKey": false,
          "notNull": true,
          "autoincrement": false,
          "default": "(datetime('now'))"
        }
      },
      "indexes": {
        "qa_criteria_issue_id_unique": {
          "name": "qa_criteria_issue_id_unique",
          "columns": [
            "issue_id"
          ],
          "isUnique": true
        }
      },
      "foreignKeys": {
        "qa_criteria_issue_id_issues_issue_id_fk": {
          "name": "qa_criteria_issue_id_issues_issue_id_fk",
          "tableFrom": "qa_criteria",
          "tableTo": "issues",
          "columnsFrom": [
            "issue_id"
          ],
          "columnsTo": [
            "issue_id"
          ],
          "onDelete": "no action",
          "onUpdate": "no action"
        }
      },
      "compositePrimaryKeys": {},
      "uniqueConstraints": {},
      "checkConstraints": {}
    },
    "results": {
      "name": "results",
      "columns": {
        "id": {
          "name": "id",
          "type": "integer",
          "primaryKey": true,
          "notNull": true,
          "autoincrement": true
        },
        "issue_id": {
          "name": "issue_id",
          "type": "integer",
          "primaryKey": false,
          "notNull": true,
          "autoincrement": false
        },
        "data": {
          "name": "data",
          "type": "text",
          "primaryKey": false,
          "notNull": true,
          "autoincrement": false
        },
        "created_at": {
          "name": "created_at",
          "type": "text",
          "primaryKey": false,
          "notNull": true,
          "autoincrement": false,
          "default": "(datetime('now'))"
        }
      },
      "indexes": {
        "results_issue_id_unique": {
          "name": "results_issue_id_unique",
          "columns": [
            "issue_id"
          ],
          "isUnique": true
        }
      },
      "foreignKeys": {
        "results_issue_id_issues_issue_id_fk": {
          "name": "results_issue_id_issues_issue_id_fk",
          "tableFrom": "results",
          "tableTo": "issues",
          "columnsFrom": [
            "issue_id"
          ],
          "columnsTo": [
            "issue_id"
          ],
          "onDelete": "no action",
          "onUpdate": "no action"
        }
      },
      "compositePrimaryKeys": {},
      "uniqueConstraints": {},
      "checkConstraints": {}
    }
  },
  "views": {},
  "enums": {},
  "_meta": {
    "schemas": {},
    "tables": {},
    "columns": {}
  },
  "internal": {
    "indexes": {}
  }
}